rtcirqus/rtcirqus.py
rtcirqus-0.2.1.dist-info/licenses/LICENSE
rtcirqus-0.2.1.dist-info/METADATA
rtcirqus-0.2.1.dist-info/WHEEL
rtcirqus-0.2.1.dist-info/entry_points.txt
rtcirqus-0.2.1.dist-info/top_level.txt
rtcirqus-0.2.1.dist-info/RECORD
