Metadata-Version: 2.4
Name: rtcirqus
Version: 0.2.1
Summary: Set real-time priorities of IRQ threads dynamically
Author-email: Jeremy Jongepier <jeremy@autostatic.com>
License-Expression: MIT
Project-URL: Homepage, https://codeberg.org/autostatic/rtcirqus
Keywords: real-time,priorities,audio
Classifier: Programming Language :: Python
Classifier: Programming Language :: Python :: 3
Classifier: Operating System :: POSIX :: Linux
Classifier: Topic :: Utilities
Classifier: Topic :: System :: Installation/Setup
Requires-Python: >=3.6
License-File: LICENSE
Requires-Dist: pyudev
Requires-Dist: pyalsaaudio
Requires-Dist: psutil
Dynamic: license-file
